py_ewr/__init__.py
py_ewr/data_inputs.py
py_ewr/evaluate_EWRs.py
py_ewr/io.py
py_ewr/observed_handling.py
py_ewr/scenario_handling.py
py_ewr/summarise_results.py
py_ewr/model_metadata/EWR_Sitelist_FIRM_20250718.csv
py_ewr/model_metadata/SiteID_MDBA.csv
py_ewr/model_metadata/SiteID_NSW.csv
py_ewr/model_metadata/iqqm_stations.csv
py_ewr/parameter_metadata/ewr_calc_config.json
py_ewr/parameter_metadata/objective_reference.csv
py_ewr/parameter_metadata/parameter_sheet.csv
py_ewr-2.3.9.dist-info/licenses/LICENSE
py_ewr-2.3.9.dist-info/METADATA
py_ewr-2.3.9.dist-info/WHEEL
py_ewr-2.3.9.dist-info/top_level.txt
py_ewr-2.3.9.dist-info/RECORD
