Metadata-Version: 2.4
Name: py_ewr
Version: 2.3.9
Summary: Environmental Water Requirement calculator
Home-page: https://github.com/MDBAuth/EWR_tool
Author: Martin Job
Author-email: Martin.Job@mdba.gov.au
Project-URL: Bug Tracker, https://github.com/MDBAuth/EWR_tool/issues
Classifier: Programming Language :: Python :: 3
Classifier: License :: OSI Approved :: GNU General Public License (GPL)
Classifier: Operating System :: OS Independent
Classifier: Development Status :: 4 - Beta
Classifier: Programming Language :: Python
Classifier: Programming Language :: Python :: 3
Classifier: Programming Language :: Python :: 3.9
Classifier: Programming Language :: Python :: 3.10
Classifier: Programming Language :: Python :: 3.11
Classifier: Programming Language :: Python :: 3.12
Classifier: Programming Language :: Python :: 3.13
Classifier: Framework :: Pytest
License-File: LICENSE
Requires-Dist: pandas>2
Requires-Dist: requests>2
Requires-Dist: mdba-gauge-getter==0.5.1
Requires-Dist: cachetools>5
Requires-Dist: xarray
Requires-Dist: h5py
Requires-Dist: netCDF4
Requires-Dist: numpy<2
Dynamic: author
Dynamic: author-email
Dynamic: classifier
Dynamic: description
Dynamic: description-content-type
Dynamic: home-page
Dynamic: license-file
Dynamic: project-url
Dynamic: requires-dist
Dynamic: summary
